omniback/_C.cpython-310-x86_64-linux-gnu.so
omniback/__init__.py
omniback/_build_info.py
omniback/_version.py
omniback/commands.py
omniback/libomniback.so
omniback/parser.py
omniback/_C/__init__.pyi
omniback/_C/backend.pyi
omniback/_C/base_types.pyi
omniback/csrc/all2numpy.hpp
omniback/csrc/any.hpp
omniback/csrc/atomic_type.hpp
omniback/csrc/backend.hpp
omniback/csrc/box.hpp
omniback/csrc/converts.hpp
omniback/csrc/dict.hpp
omniback/csrc/py_helper.hpp
omniback/csrc/py_register.hpp
omniback/csrc/python.hpp
omniback/csrc/register.hpp
omniback/include/omniback/extension.hpp
omniback/include/omniback/builtin/aspect.hpp
omniback/include/omniback/builtin/basic_backends.hpp
omniback/include/omniback/builtin/benchmark.hpp
omniback/include/omniback/builtin/box.hpp
omniback/include/omniback/builtin/cat_split.hpp
omniback/include/omniback/builtin/condition.hpp
omniback/include/omniback/builtin/control_plane.hpp
omniback/include/omniback/builtin/generate_backend.hpp
omniback/include/omniback/builtin/identity.hpp
omniback/include/omniback/builtin/interpreter.hpp
omniback/include/omniback/builtin/ioc.hpp
omniback/include/omniback/builtin/key_operator.hpp
omniback/include/omniback/builtin/launch.hpp
omniback/include/omniback/builtin/or.hpp
omniback/include/omniback/builtin/page_table.hpp
omniback/include/omniback/builtin/proxy.hpp
omniback/include/omniback/builtin/register_node.hpp
omniback/include/omniback/builtin/result_parser.hpp
omniback/include/omniback/builtin/result_queue.hpp
omniback/include/omniback/builtin/select.hpp
omniback/include/omniback/builtin/sequential.hpp
omniback/include/omniback/builtin/source.hpp
omniback/include/omniback/builtin/tree.hpp
omniback/include/omniback/core/any.hpp
omniback/include/omniback/core/backend.hpp
omniback/include/omniback/core/dict.hpp
omniback/include/omniback/core/event.hpp
omniback/include/omniback/core/general_queue.hpp
omniback/include/omniback/core/helper.hpp
omniback-1.50.1.dist-info/LICENSE
omniback-1.50.1.dist-info/METADATA
omniback-1.50.1.dist-info/WHEEL
omniback-1.50.1.dist-info/top_level.txt
omniback-1.50.1.dist-info/RECORD
